django_cricket_statistics/__init__.py
django_cricket_statistics/admin.py
django_cricket_statistics/apps.py
django_cricket_statistics/models.py
django_cricket_statistics/migrations/0001_initial.py
django_cricket_statistics/migrations/__init__.py
django_cricket_statistics/views/__init__.py
django_cricket_statistics/views/batting.py
django_cricket_statistics/views/bowling.py
django_cricket_statistics/views/common.py
django_cricket_statistics/views/fielding.py
django_cricket_statistics/views/misc.py
django_cricket_statistics/views/wicketkeeping.py
django_cricket_statistics-0.0.1.dist-info/LICENSE
django_cricket_statistics-0.0.1.dist-info/METADATA
django_cricket_statistics-0.0.1.dist-info/WHEEL
django_cricket_statistics-0.0.1.dist-info/top_level.txt
django_cricket_statistics-0.0.1.dist-info/RECORD
